README.rst
setup.py
mattermost_log_handler/__init__.py
mattermost_log_handler.egg-info/PKG-INFO
mattermost_log_handler.egg-info/SOURCES.txt
mattermost_log_handler.egg-info/dependency_links.txt
mattermost_log_handler.egg-info/requires.txt
mattermost_log_handler.egg-info/top_level.txt